gendbox/__init__.py
gendbox/geometry.py
gendbox/stats.py
gendbox/utils.py
gendbox/learning/__init__.py
gendbox/learning/supervised.py
gendbox/preprocessing/__init__.py
gendbox/preprocessing/normalization.py
gendbox/preprocessing/splitting.py
preprocessing/__init__.py
preprocessing/normalization.py
gendbox-0.2.2.dist-info/LICENSE
gendbox-0.2.2.dist-info/METADATA
gendbox-0.2.2.dist-info/WHEEL
gendbox-0.2.2.dist-info/top_level.txt
gendbox-0.2.2.dist-info/RECORD
