Metadata-Version: 2.1
Name: gendbox
Version: 0.2.2
Summary: Açıklama
Author: Candaş Koru
License-File: LICENSE
